README.md
setup.py
src/interpolation/__init__.py
src/interpolation/envelope_warp.py
src/interpolation/envelope_warp_editor.py
src/interpolation/envelope_warp_overlay.py
src/interpolation/interpolate_v4.py
src/interpolation/deepsvg/__init__.py
src/interpolation/deepsvg/config.py
src/interpolation/deepsvg/svg_dataset.py
src/interpolation/deepsvg/svgtensor_dataset.py
src/interpolation/deepsvg/svgtensor_dataset0.py
src/interpolation/deepsvg/train.py
src/interpolation/deepsvg/difflib/__init__.py
src/interpolation/deepsvg/difflib/loss.py
src/interpolation/deepsvg/difflib/tensor.py
src/interpolation/deepsvg/difflib/utils.py
src/interpolation/deepsvg/gui/__init__.py
src/interpolation/deepsvg/gui/config.py
src/interpolation/deepsvg/gui/interpolate.py
src/interpolation/deepsvg/gui/main.py
src/interpolation/deepsvg/gui/utils.py
src/interpolation/deepsvg/gui/layout/__init__.py
src/interpolation/deepsvg/gui/layout/aligned_textinput.py
src/interpolation/deepsvg/gui/state/__init__.py
src/interpolation/deepsvg/gui/state/project.py
src/interpolation/deepsvg/gui/state/state.py
src/interpolation/deepsvg/model/__init__.py
src/interpolation/deepsvg/model/basic_blocks.py
src/interpolation/deepsvg/model/config.py
src/interpolation/deepsvg/model/loss.py
src/interpolation/deepsvg/model/model.py
src/interpolation/deepsvg/model/utils.py
src/interpolation/deepsvg/model/layers/__init__.py
src/interpolation/deepsvg/model/layers/attention.py
src/interpolation/deepsvg/model/layers/functional.py
src/interpolation/deepsvg/model/layers/improved_transformer.py
src/interpolation/deepsvg/model/layers/positional_encoding.py
src/interpolation/deepsvg/model/layers/transformer.py
src/interpolation/deepsvg/model/layers/utils.py
src/interpolation/deepsvg/model_original/__init__.py
src/interpolation/deepsvg/model_original/basic_blocks.py
src/interpolation/deepsvg/model_original/config.py
src/interpolation/deepsvg/model_original/loss.py
src/interpolation/deepsvg/model_original/model.py
src/svg_func.egg-info/PKG-INFO
src/svg_func.egg-info/SOURCES.txt
src/svg_func.egg-info/dependency_links.txt
src/svg_func.egg-info/top_level.txt